zendron/__init__.py
zendron/__main__.py
zendron/annotations.py
zendron/bibtex.py
zendron/cache.py
zendron/cache_deprecated.py
zendron/comments.py
zendron/config.py
zendron/date.py
zendron/dry_remove.py
zendron/front.py
zendron/init.py
zendron/items.py
zendron/load.py
zendron/load_since_cache.py
zendron/metadata.py
zendron/remove.py
zendron/sync.py
zendron/user_citation_key.py
zendron/conf/zendron/__init__.py
zendron/conf/zendron/config_template.yaml
zendron/conf/zendron/default_template.yaml
zendron/pods/dendron.markdown/config.import.yml
zendron-1.4.1.dist-info/LICENSE
zendron-1.4.1.dist-info/METADATA
zendron-1.4.1.dist-info/WHEEL
zendron-1.4.1.dist-info/entry_points.txt
zendron-1.4.1.dist-info/top_level.txt
zendron-1.4.1.dist-info/RECORD
