Metadata-Version: 2.1
Name: zendron
Version: 1.4.1
Summary: Import Zotero annotations with Dendron integration. https://github.com/Mjvolk3/Zendron
Author-email: Michael Volk <michaeljvolk7@gmail.com>
License: MIT License
Project-URL: Homepage, https://github.com/Mjvolk3/Zendron
Keywords: Zotero,Dendron,Markdown,Notes,Annotations,VSCode
Classifier: License :: OSI Approved :: MIT License
Classifier: Programming Language :: Python
Classifier: Programming Language :: Python :: 3
Requires-Python: >=3.10
License-File: LICENSE
Requires-Dist: hydra-core >=1.3.1
Requires-Dist: tqdm >=4.64.1
Requires-Dist: pyzotero >=1.5.5
Requires-Dist: tomli >=2.0.1
Requires-Dist: python-frontmatter >=1.0.0
Requires-Dist: html2text >=2020.1.16
Requires-Dist: Markdown >=3.4.1
Requires-Dist: markdownify >=0.11.6
Requires-Dist: importlib-metadata >=6.6.0
Provides-Extra: dev
Requires-Dist: black ; extra == 'dev'
Requires-Dist: pip-tools ; extra == 'dev'
Requires-Dist: pytest ; extra == 'dev'
Requires-Dist: python-semantic-release ; extra == 'dev'
Requires-Dist: build ; extra == 'dev'
